flexible_partial/LICENSE
flexible_partial/README.MD
flexible_partial/__init__.py
flexible_partial/requirements.txt
flexible_partial/thirdparty.json
flexible_partial-0.12.dist-info/LICENSE.rst
flexible_partial-0.12.dist-info/METADATA
flexible_partial-0.12.dist-info/WHEEL
flexible_partial-0.12.dist-info/top_level.txt
flexible_partial-0.12.dist-info/RECORD
